molgrid.libs/libbz2-a273e504.so.1.0.6
molgrid-0.5.5.dist-info/METADATA
molgrid-0.5.5.dist-info/RECORD
molgrid-0.5.5.dist-info/WHEEL
molgrid-0.5.5.dist-info/top_level.txt
molgrid/molgrid.so
molgrid/__init__.py
molgrid/torch_bindings.py
